beetle_logging/__init__.py
beetle_logging/main.py
beetle_logging-1.0.0.dist-info/WHEEL
beetle_logging-1.0.0.dist-info/entry_points.txt
beetle_logging-1.0.0.dist-info/METADATA
beetle_logging-1.0.0.dist-info/RECORD
