Metadata-Version: 2.3
Name: beetle-logging
Version: 1.0.0
Summary: A python package with extra tools for the python logging package
Requires-Python: >=3.10
